gestao_aluguer/__init__.py
gestao_aluguer/gestao_aluguer.py
gestao_aluguer_veiculos-1.1.5.dist-info/licenses/LICENSE.txt
gestao_aluguer_veiculos-1.1.5.dist-info/METADATA
gestao_aluguer_veiculos-1.1.5.dist-info/WHEEL
gestao_aluguer_veiculos-1.1.5.dist-info/top_level.txt
gestao_aluguer_veiculos-1.1.5.dist-info/RECORD
